pypco/__init__.py
pypco/auth_config.py
pypco/exceptions.py
pypco/pco.py
pypco/user_auth_helpers.py
pypco-1.2.0.dist-info/LICENSE
pypco-1.2.0.dist-info/METADATA
pypco-1.2.0.dist-info/WHEEL
pypco-1.2.0.dist-info/top_level.txt
pypco-1.2.0.dist-info/zip-safe
pypco-1.2.0.dist-info/RECORD
