Metadata-Version: 2.1
Name: pypco
Version: 1.2.0
Summary: A Python wrapper for the Planning Center Online API.
Home-page: https://github.com/billdeitrick/pypco
Author: Bill Deitrick
Author-email: hello@billdeitrick.com
License: MIT
Classifier: Development Status :: 5 - Production/Stable
Classifier: Intended Audience :: Developers
Classifier: License :: OSI Approved :: MIT License
Classifier: Operating System :: OS Independent
Classifier: Programming Language :: Python :: 3.7
Classifier: Programming Language :: Python :: 3.8
Classifier: Programming Language :: Python :: 3.9
Classifier: Programming Language :: Python :: 3.10
Classifier: Programming Language :: Python :: 3.11
Classifier: Topic :: Software Development :: Libraries
Requires-Python: >=3.7.0
License-File: LICENSE
Requires-Dist: requests
